li/__init__.py
li/bitcoin_rpc_class.py
li/dialog.ui
li/issue.py
li/main.py
LiquidIssuer-0.2.dist-info/LICENSE
LiquidIssuer-0.2.dist-info/METADATA
LiquidIssuer-0.2.dist-info/WHEEL
LiquidIssuer-0.2.dist-info/entry_points.txt
LiquidIssuer-0.2.dist-info/top_level.txt
LiquidIssuer-0.2.dist-info/RECORD
